Metadata-Version: 2.1
Name: uitools
Version: 0.0.2
Summary: UITools project
Home-page: https://github.com/criojag/UITools
Author: César Rioja García
Author-email: criojag1200@alumno.ipn.mx
License: MIT
Keywords: seaborn
Platform: UNKNOWN
Classifier: 
Classifier: 
License-File: LICENSE.txt
